gcmtools/__init__.py
gcmtools-0.5.8.dist-info/LICENSE.txt
gcmtools-0.5.8.dist-info/METADATA
gcmtools-0.5.8.dist-info/WHEEL
gcmtools-0.5.8.dist-info/top_level.txt
gcmtools-0.5.8.dist-info/RECORD
