Metadata-Version: 2.1
Name: gcmtools
Version: 0.5.8
Summary: GCM Output Analysis Tools
Home-page: https://github.com/alphaparrot/gcmtools
Author: Adiv Paradise
Author-email: paradise.astro@gmail.com
License: GNU General Public License
Platform: UNKNOWN
Requires-Dist: numpy
Requires-Dist: netCDF4
Requires-Dist: matplotlib
Requires-Dist: scipy
